{
  "creds": {
    "noiseKey": {
      "private": {
        "type": "Buffer",
        "data": "sK6Wr8qFLaq2Ib9P4wzGbFFJK9XYSM7VjnAE6CRwknU="
      },
      "public": {
        "type": "Buffer",
        "data": "SA5sPomjQUnl2NC6fKBQmS3ss6MoYdjAKeqI9/t+7n0="
      }
    },
    "signedIdentityKey": {
      "private": {
        "type": "Buffer",
        "data": "oHd1mQAdHs3VWcYsAzvl7zEVyHfjoudf5Mg23q6TZG8="
      },
      "public": {
        "type": "Buffer",
        "data": "Uo68l6WtdOHZJl44y+pPhBXFb7RcBuDsu/cX3xw1ywg="
      }
    },
    "signedPreKey": {
      "keyPair": {
        "private": {
          "type": "Buffer",
          "data": "sK1Y9vkaj55JbtDLuEkRXLdVysuSYccKvu+OOA6gp0U="
        },
        "public": {
          "type": "Buffer",
          "data": "9I3ph5ANG3idPyrBCTjuv2xNGGtUkYWG2+6xrGAmpzg="
        }
      },
      "signature": {
        "type": "Buffer",
        "data": "CuX+Ni684yW9aae7ktUkYvEZ1oxRZyF1VWG2Qia3BX9VqVaXcQeY9XUuHalRL9TKgPGjl7SmVpxe11La+5Q8hw=="
      },
      "keyId": 1
    },
    "registrationId": 119,
    "advSecretKey": "4uM7npxQsX5S/IRReuznRrVNbpBDbLJcDBSYESbB7CY=",
    "processedHistoryMessages": [
      {
        "key": {
          "remoteJid": "19546420233@s.whatsapp.net",
          "fromMe": true,
          "id": "37A558B664EEE49D32E08E3A642F6A64"
        },
        "messageTimestamp": 1669366844
      },
      {
        "key": {
          "remoteJid": "19546420233@s.whatsapp.net",
          "fromMe": true,
          "id": "6C03537571B75AE80D176ADD523C330D"
        },
        "messageTimestamp": 1669366845
      },
      {
        "key": {
          "remoteJid": "19546420233@s.whatsapp.net",
          "fromMe": true,
          "id": "3957F6FE54C70F13F8880EDB67DC0BFF"
        },
        "messageTimestamp": 1669366854
      }
    ],
    "nextPreKeyId": 31,
    "firstUnuploadedPreKeyId": 31,
    "accountSettings": {
      "unarchiveChats": false
    },
    "account": {
      "details": "CM7K65EHELaIgpwGGAE=",
      "accountSignatureKey": "UDoinvw9tTky9SoF9kvjR4ZWC3n6dKFzDxR8A+S1cUs=",
      "accountSignature": "umP3Vv1FZGs+n9RkFjfEXHwN1rh9Yu0Ym6OzKksZRXrh37qn0MFz8pxjdPcUWhpUCboJwaEMtBBSuOwi0kS+Ag==",
      "deviceSignature": "CwBf3DZalx0LEHlvxJZ8KqwKXAEOdnTesoQLvUEcDW/Bb+VsQ7B67hqq9v2PeU0vNAUnFMg/m1efQ4bPwvgFjQ=="
    },
    "me": {
      "id": "19546420233:1@s.whatsapp.net",
      "name": "P"
    },
    "signalIdentities": [
      {
        "identifier": {
          "name": "19546420233:1@s.whatsapp.net",
          "deviceId": 0
        },
        "identifierKey": {
          "type": "Buffer",
          "data": "BVA6Ip78PbU5MvUqBfZL40eGVgt5+nShcw8UfAPktXFL"
        }
      }
    ],
    "platform": "android",
    "lastAccountSyncTimestamp": 1669366841,
    "myAppStateKeyId": "AAAAAJcn"
  },
  "keys": {
    "preKeys": {
      "1": {
        "private": {
          "type": "Buffer",
          "data": "8Iptt4wNE6rPQjCFIkdBUFyiGJYpYWzv+Iwx1mw46Fw="
        },
        "public": {
          "type": "Buffer",
          "data": "hvXdJJxD5AIqrlwRhEN92zOCfczvTUKeRMvrOPjeuwg="
        }
      },
      "2": {
        "private": {
          "type": "Buffer",
          "data": "WBDFwxPLvUe8RnlidTbzqIx4gWzd8qX+/ZxlT44Wk1g="
        },
        "public": {
          "type": "Buffer",
          "data": "YbmFuzeZJEoV+ZKDKnPsugeoEzqLzockKGqTFwjaIQM="
        }
      },
      "3": {
        "private": {
          "type": "Buffer",
          "data": "AFFyJ2fg/DfLFx0QdoyNddUj3f7cSlDBBaxQY3g9Ymw="
        },
        "public": {
          "type": "Buffer",
          "data": "uQJBhZTvoexRoGwKFdrJcKE+VTwgeYVCxXXyVsyewVw="
        }
      },
      "4": {
        "private": {
          "type": "Buffer",
          "data": "oMKaajCkWU8igiSEhsWvyXqxj1RzvSRkoxo6Sy2OdWQ="
        },
        "public": {
          "type": "Buffer",
          "data": "H1Na9XNx7/+GE2GOjm3HZ89yh9cplHEpaNGDkG4/X2g="
        }
      },
      "5": {
        "private": {
          "type": "Buffer",
          "data": "cNaYI5nYL59Z7dZ345Lleaga7ed/YVBmjJloQu/Hy0s="
        },
        "public": {
          "type": "Buffer",
          "data": "lpbCyWGbl1mGlVIbbZr0zjjsP1Afh37vJBQqsujxXE4="
        }
      },
      "6": {
        "private": {
          "type": "Buffer",
          "data": "uE5yoELpt75j0jOxGhgxoo0ssQ9XSnZMm5+lG6+dnVM="
        },
        "public": {
          "type": "Buffer",
          "data": "UKd7TT+1iJEhI4ZUVS6sB/3/IBoqYIFvU35VOjbXCiY="
        }
      },
      "7": {
        "private": {
          "type": "Buffer",
          "data": "QBmbIuv/qvWSs3QiMrpKSlmwafvzwAJYm0BWT+DD7W8="
        },
        "public": {
          "type": "Buffer",
          "data": "+xyYvbPrZxQp/ZsXpMqPQH2DP6l/GEXpPb87iNQZj0c="
        }
      },
      "8": {
        "private": {
          "type": "Buffer",
          "data": "ADJvCoD6/g8BwUqsyj9owNswoxzmLxc+x9uey0Aw/H8="
        },
        "public": {
          "type": "Buffer",
          "data": "j644fOVpO3vN8rcUSUxw9Y5RPr8XpZLRlASk2RhNji8="
        }
      },
      "9": {
        "private": {
          "type": "Buffer",
          "data": "+D/tWqFi2Kk24U/c/iYDLdJkL2tAc0eRoIO4p6J5pn0="
        },
        "public": {
          "type": "Buffer",
          "data": "jAFxRvRXmdXc7onfjbKpNPXsajeXgaVWft6BDh2STlw="
        }
      },
      "10": {
        "private": {
          "type": "Buffer",
          "data": "KHR4/Y4b9I6+65qsH5dCBdYAapkavpGXcef/0a4/uXI="
        },
        "public": {
          "type": "Buffer",
          "data": "M39cAlk3ErtXdIcyGqTlfrwrN8VDeanBF00oPnfqOFE="
        }
      },
      "11": {
        "private": {
          "type": "Buffer",
          "data": "6FjhlaY52H6A98b5Rtms1DbAj2kZy+VGVu7qKYiTfHo="
        },
        "public": {
          "type": "Buffer",
          "data": "ZfRZZYZvVbFykD8XkM0YoS/bdokC+Fp8BuirbAhlEks="
        }
      },
      "12": {
        "private": {
          "type": "Buffer",
          "data": "AHJJW2WpOaP2RrUWQKuIBqN7FTAbnXocINCwWl7WK20="
        },
        "public": {
          "type": "Buffer",
          "data": "bNCKvzlb6VLVUptnAZQoqtNnsBGGCTb3Y2JvmnihewM="
        }
      },
      "13": {
        "private": {
          "type": "Buffer",
          "data": "0JWanluvHH6NuEZwh6wDpFi+95fp/VI43IimG12GvEc="
        },
        "public": {
          "type": "Buffer",
          "data": "vTnQvcJTKkYP7EFHlfbnvvaK8nv+706ZqZYko5DqHhA="
        }
      },
      "14": null,
      "15": {
        "private": {
          "type": "Buffer",
          "data": "iDhaSvWZ26x7Rk4XqweWliO1LJqZ4QFVhZTeg8pTFGU="
        },
        "public": {
          "type": "Buffer",
          "data": "j6xUdPGWw8p9zH8nQtEvdOuSsy9e/niaWRzgJxVCJmY="
        }
      },
      "16": {
        "private": {
          "type": "Buffer",
          "data": "mGmH5rkAFXjMn+25JgVJRNT8e+0ltzMNF5ewo1mUHkU="
        },
        "public": {
          "type": "Buffer",
          "data": "A/2tG+tXrCBRwMDIFEDObwGslKI3bOccbnzmmuYysQo="
        }
      },
      "17": {
        "private": {
          "type": "Buffer",
          "data": "iLWeKHezDZLJDgZbRniF3sRKDzW/ILyOLCnQ4GfxknI="
        },
        "public": {
          "type": "Buffer",
          "data": "g7todJiBr0CMxly6LN1DVsC177cdYKo2QSJXCz8lMks="
        }
      },
      "18": {
        "private": {
          "type": "Buffer",
          "data": "OMh7eP+PykT4QIbzP+xynWn5wDY6o1Ss4/dRmuDCFls="
        },
        "public": {
          "type": "Buffer",
          "data": "dnLOEVQoeoL2K2wnldw5m6RrghJxDXL2gWsimW+6AxE="
        }
      },
      "19": {
        "private": {
          "type": "Buffer",
          "data": "UNQbgJTJhOaJ5rpkYZcJzwWQHmOM2WJLKCnA+8JF8nU="
        },
        "public": {
          "type": "Buffer",
          "data": "mtjYC5heh/TCvA0p/umzXV5U1Y1zL8JCfey8gPxPc0g="
        }
      },
      "20": {
        "private": {
          "type": "Buffer",
          "data": "wDIIjYSiV5LxCvU6UN54424Zv33JA65aewOoYbmDE2k="
        },
        "public": {
          "type": "Buffer",
          "data": "cvPi8ku+AnBICVQbzkm1IMs/zi+ebjGKdssPw9NDpmM="
        }
      },
      "21": {
        "private": {
          "type": "Buffer",
          "data": "8A3EmCvZ/A9/JnhvJYvcPFSQK4CVPrsDtkNyEj0OJ0k="
        },
        "public": {
          "type": "Buffer",
          "data": "fiNQK9OyIkNXcqHLqmpyu789TjKQmuRFWOvTNZSoank="
        }
      },
      "22": {
        "private": {
          "type": "Buffer",
          "data": "kJthOMG4z0y/EY1DiRwzDbxCBUUuMIQTceXxltBNik8="
        },
        "public": {
          "type": "Buffer",
          "data": "qwoW+3GaXwUaUwR7vtHwl4q+OsDz73hHpGF52GbEdQU="
        }
      },
      "23": {
        "private": {
          "type": "Buffer",
          "data": "kJ3EOBWpqlXMowEDP6WFah+UATPlMK/RFYaIuo5En0o="
        },
        "public": {
          "type": "Buffer",
          "data": "gyswMvD0kral1LyZFxonrnn4U91ahPAXl+GMC4XsRgw="
        }
      },
      "24": {
        "private": {
          "type": "Buffer",
          "data": "gDeSs66HAytBoK7Dbxab6Li72FMxnD4DYpGFer2bcGw="
        },
        "public": {
          "type": "Buffer",
          "data": "mFW2zp4S+s/yruoIcYHWBWBx6dOssLi8Mh2tL20/oUE="
        }
      },
      "25": {
        "private": {
          "type": "Buffer",
          "data": "uO7hV3U3LobiBLToB2BKMlws47oiyVNnaJ5u5oK5g1s="
        },
        "public": {
          "type": "Buffer",
          "data": "ZrG+608voJSyNIaNV44zQC5SqilzS3P4YUDcXf08nRE="
        }
      },
      "26": {
        "private": {
          "type": "Buffer",
          "data": "4AChfTf1ZeV/fsj28UX4DXGqjK6fkwdv7zHIvUa4UnI="
        },
        "public": {
          "type": "Buffer",
          "data": "nhemAqj0rZ8OnXOJ1znSnCmjV7/9LPq3kkKXPWn9/j0="
        }
      },
      "27": {
        "private": {
          "type": "Buffer",
          "data": "gM9CpkRB1+zzZjXzyePADUGhAw4CSerunOG4y6T2PG4="
        },
        "public": {
          "type": "Buffer",
          "data": "a6g6x0fNPxaPV7aqewb7BdO+pB5awe6YGAT/u4dpj0g="
        }
      },
      "28": {
        "private": {
          "type": "Buffer",
          "data": "qCXxlJu3hzdNs99eMlc5eIAH0CX4vbNQbuo3WIDxm1o="
        },
        "public": {
          "type": "Buffer",
          "data": "ZHHYFaE8GqwPzywRb7gfWdZUJLmL+c57gRSwQ8bX1DA="
        }
      },
      "29": {
        "private": {
          "type": "Buffer",
          "data": "QFg3e3KgdMzuxTAguY6EZAOUrkBmW7LFqqPDwANcmng="
        },
        "public": {
          "type": "Buffer",
          "data": "WomcohLJ93jFUsw+eQHvIpajDSLRCRfHMIPuUMxfQQU="
        }
      },
      "30": null
    },
    "sessions": {
      "19546420233.0": {
        "_sessions": {
          "BQWCr/RfqAucpGPyQ1I1xjY+Jr+wrO1o8LuW3o93wIUO": {
            "registrationId": 720371274,
            "currentRatchet": {
              "ephemeralKeyPair": {
                "pubKey": "BVP+oeHmmuqXOaciujhJ1iGmzKr7PUOvVMHFfNVQglJ4",
                "privKey": "COvVRnbLeFdzAMlqTHTyTqoYgvrKw4/mB5QIc/BjkXA="
              },
              "lastRemoteEphemeralKey": "BXKnxy2MJKP469b8LHn5qSco6G72hfGVJsa3+rIDndIZ",
              "previousCounter": 0,
              "rootKey": "c/q5prri7g8+OihchjzWJB9Doa1Fc9WNZyg0xFqrdKU="
            },
            "indexInfo": {
              "baseKey": "BQWCr/RfqAucpGPyQ1I1xjY+Jr+wrO1o8LuW3o93wIUO",
              "baseKeyType": 2,
              "closed": -1,
              "used": 1669366843456,
              "created": 1669366843456,
              "remoteIdentityKey": "BVA6Ip78PbU5MvUqBfZL40eGVgt5+nShcw8UfAPktXFL"
            },
            "_chains": {
              "BXKnxy2MJKP469b8LHn5qSco6G72hfGVJsa3+rIDndIZ": {
                "chainKey": {
                  "counter": 9,
                  "key": "SIyvuo49uD8MEjQdC8bdVjX8b6SMs9OOwis54m8H044="
                },
                "chainType": 2,
                "messageKeys": {}
              },
              "BVP+oeHmmuqXOaciujhJ1iGmzKr7PUOvVMHFfNVQglJ4": {
                "chainKey": {
                  "counter": -1,
                  "key": "a85B2oJHE0WXN3eYdoNqSq20JXKygErqFt0eQRmwiK0="
                },
                "chainType": 1,
                "messageKeys": {}
              }
            }
          }
        },
        "version": "v1"
      },
      "6283172862360:35.0": {
        "_sessions": {
          "BW8urcVLJAoYUcGHaGIi67luQhLohNiC+Tm+nfC3NU11": {
            "registrationId": 79,
            "currentRatchet": {
              "ephemeralKeyPair": {
                "pubKey": "BRYGhN8DT+zk8TD4ZrNJ76o6D4P/+P19sI3B5ojlBVpJ",
                "privKey": "IAiR1vYV2bHWnzxLwuOCDBXKNuJTIF9riWOWfuc/C1U="
              },
              "lastRemoteEphemeralKey": "BVvqyTsPSKS7cco8z9Pn7nsKCnPpIbABNFvVqiaxvjoH",
              "previousCounter": 0,
              "rootKey": "eArBV0SdAQMeFI1xR4N1kDKZ4WgiJWAccq33flPOVUg="
            },
            "indexInfo": {
              "baseKey": "BW8urcVLJAoYUcGHaGIi67luQhLohNiC+Tm+nfC3NU11",
              "baseKeyType": 2,
              "closed": -1,
              "used": 1669366865317,
              "created": 1669366865317,
              "remoteIdentityKey": "BetSO6xr3LjVS0sXATdzG64IVGW+E96tc7iO9hKGyqJ4"
            },
            "_chains": {
              "BVvqyTsPSKS7cco8z9Pn7nsKCnPpIbABNFvVqiaxvjoH": {
                "chainKey": {
                  "counter": 0,
                  "key": "OhgTfUm9CSZWPSGRXzf6Evd5pVPeyJF+JcmaKEtQPs4="
                },
                "chainType": 2,
                "messageKeys": {}
              },
              "BRYGhN8DT+zk8TD4ZrNJ76o6D4P/+P19sI3B5ojlBVpJ": {
                "chainKey": {
                  "counter": -1,
                  "key": "7GEcNeuWv9wDMRZqSntWInR2NDzdhGEKL68yvPuW7u0="
                },
                "chainType": 1,
                "messageKeys": {}
              }
            }
          }
        },
        "version": "v1"
      }
    },
    "appStateSyncKeys": {
      "AAAAAJcn": {
        "keyData": "OxTQQk3Z2lhmAuRhrmdDZrNZE0hyfqviDCs/+6ggKEY=",
        "fingerprint": {
          "rawId": 1916462414,
          "currentIndex": 1,
          "deviceIndexes": [
            0,
            1
          ]
        },
        "timestamp": "1669366843603"
      }
    },
    "appStateVersions": {
      "critical_block": {
        "version": 1,
        "hash": {
          "type": "Buffer",
          "data": "L9lTBEuqmHVVEfzunfb67BhD1LDyq71z9AWk1f81wOGLzwR+a08TvorbzsfHvicokBaTtnDY/i6/C+PH30TzndeJTsgBTBi8iKhvSdhkuJLds7RntrhAgkfKbEE/7rGoBhrOF6nyhmmXIoX9RNDHED5nYaEtw1P4LVvKT/H1oTE="
        },
        "indexValueMap": {
          "0r0dhEH+SKn5Dn23XAM1NVApENp9PC6YHSsVg+Q+zls=": {
            "valueMac": {
              "type": "Buffer",
              "data": "Kr6OWMMMFYf3hqMpK0Qh9wflt0gIVQruSQVmfnndGAA="
            }
          },
          "1/Zgojvd5IxDOd7IeSlMgQNsUHTqZcd03SuqKaBrqfM=": {
            "valueMac": {
              "type": "Buffer",
              "data": "13GpKGGDHhGpTTDICjT/UoSxcK4gMvVCELSY61sLoY0="
            }
          }
        }
      },
      "regular": {
        "version": 1,
        "hash": {
          "type": "Buffer",
          "data": "tkOl2AjLG3sa1WW/U+dH14SRj605R1U1I+g7gb9eonHbfnZ3DIeLD6xa/s0aO3zpLqV92EWLD6h4HDlLevBn5prMtAajuFQG9VYjURauAhJvdNX/496nXlDEwY+49teq7UQm9DwTd6dwxMvdj3Hm480ETY9+So3Each/myXzfOs="
        },
        "indexValueMap": {
          "vJKGlGsWBx0bsBaWBOtw7qDC96UxpmAy0skFOPF3bDM=": {
            "valueMac": {
              "type": "Buffer",
              "data": "CbJGDyCDcEQ71JJ2hBPS1rEDDuw/FAh68OPrJgrj07M="
            }
          }
        }
      },
      "critical_unblock_low": {
        "version": 1,
        "hash": {
          "type": "Buffer",
          "data": "oaaa6JPoOc/dYg13qZ1I8e6lqnTp/MayIBN9lj6PIBfAQ+t3TV8KIDThPahCVwqiX9XSZaaLuU7c/Bij+qyqeqwmjdj63mf58NVP7Vdck+4KME6RfhaGDReJStqhkFi6DAt8go2g3IonZKxWq34p/j+kfoitPFd8ZOd2YbaTVDE="
        },
        "indexValueMap": {
          "GMQhZyDAsqqNgeuXxOBTaWKGwmIeGwOKwesQInvQqnU=": {
            "valueMac": {
              "type": "Buffer",
              "data": "6w4fkv3VwTaWeFj0mF76Q9hCQn9u4LAGzdAH1PVTOeQ="
            }
          },
          "qotfsUsBhPe3CD1BjuHjXyG2OLmpVkd18tyqPqlFwMI=": {
            "valueMac": {
              "type": "Buffer",
              "data": "CHGQ5O7/whk1PCU3LgFB0iI/uAJv8Jpg3ZVbUC/ggQw="
            }
          },
          "v5SzNW7Lg+3pvEicm3gGTidNAr8rEZvqV94xsCyRx3w=": {
            "valueMac": {
              "type": "Buffer",
              "data": "aVfwu5de+sFjqz2Itccmw5TXelZasewwO4v6umTP/Vc="
            }
          },
          "6AOtSx9PxHP5axW4NN+Hf5O0ofW2RV/0pqVK8SvUe8k=": {
            "valueMac": {
              "type": "Buffer",
              "data": "LiHFqfGF86uY+Japb65hSoKSwb41qntH1izac0mR5tY="
            }
          },
          "6+CRukgyLtXB1xif1FF38P09iWT4jBww1eE75vVAXkY=": {
            "valueMac": {
              "type": "Buffer",
              "data": "N0qUzpB5X+j5gqCvhlMUhtJcc3FJhO0KdH7D7X2ohhk="
            }
          },
          "rDgg5iIgi9YHOGv/DYUswF/KadIplTpK9KMwtss0KxE=": {
            "valueMac": {
              "type": "Buffer",
              "data": "oQxJFC5ytw7rsz8hVUuxajOzX7WII7qkNwo/d9aw24E="
            }
          },
          "pqSreqnXevQd3qRpdODd3CYXHXEnNCU4xGnqutZ/Pfc=": {
            "valueMac": {
              "type": "Buffer",
              "data": "NKGlqqpr5YyzxzhLUYllmonrCEWii/Kg5A+wPhHt834="
            }
          },
          "Q8mkt1aB8tfKJjKCUHkgU0mBObP6QfdwDO5PbSfmrOE=": {
            "valueMac": {
              "type": "Buffer",
              "data": "19ToSk3fNNQc6MLA/towTXeCGuGM/wLv/UUm+cqF8To="
            }
          },
          "q0WarNJ1BnxIdDCpajdjszqW12S5FhK4Q4vJYLsfymI=": {
            "valueMac": {
              "type": "Buffer",
              "data": "P2hEEtLsKXJ7SPgNYgKInipSsnFXBxaA+YmBK2aYjHk="
            }
          },
          "CvbqB3LHlN+m+Z1mkbOgu9Q1F64EU3Rvu4nArlQ6xd4=": {
            "valueMac": {
              "type": "Buffer",
              "data": "cJaesUbwY8uOO40uOkHm+gJHiQuHkLUBJFN2DIElVgg="
            }
          },
          "koLKYJRK+2fvoapjJzpQ1bef+3dgK0P2rTrdgmXrnjk=": {
            "valueMac": {
              "type": "Buffer",
              "data": "mywkjeJ40eJDCAYGGV47Ft1Z9QYCP/RWkRCemvD5wLg="
            }
          },
          "FuVvGbHknyG+sWTxNoUXq67drMFucJabCO2gGIZUbmw=": {
            "valueMac": {
              "type": "Buffer",
              "data": "+C8Qov7D8MBuy0f73BwHgJHWnKv1hjZrN4FlJorR144="
            }
          },
          "9Ui67A/pk4SjR+Fp7Y7nty7UHGvdD2Ai7Gv16dJ8Ueo=": {
            "valueMac": {
              "type": "Buffer",
              "data": "9QdFZNQCqAQtoqzBPI/5L/Bs7Xg+V12FjxsGyobaonM="
            }
          },
          "AbZsNPSDSZ8pxG31xP4eMeFeJEotdR4V14lZ8/o6oVM=": {
            "valueMac": {
              "type": "Buffer",
              "data": "hxz8iogr12GQ+U/HbzIBIE2OJcsVwMdCsV8t/eu1Zpw="
            }
          },
          "TXk5bBPzk3iqDI4u5JNNEp9CKU7yC3hTl4D92nhP0K4=": {
            "valueMac": {
              "type": "Buffer",
              "data": "Ztwo1JprPcWX4rGqaRV5BC5YvMZCPFeD1wtt/jXFt4Q="
            }
          },
          "PC2ymEnGa5mKwbIsMR7mOlYLa0vxoTR+zjBqNcFb0/0=": {
            "valueMac": {
              "type": "Buffer",
              "data": "BRe9KZZJJhigEFFP53EJiWLc1jCmXycSzQ80cw94JXY="
            }
          },
          "r/mX65169VtyCEefx1dcM+y/VpCd0ZP7PIlkWVVhHXc=": {
            "valueMac": {
              "type": "Buffer",
              "data": "PEu5TXT/XkwoMAuYrj+aipTM7r6RvIWctk5liCbGAB0="
            }
          },
          "JPSTPMTOYNy30jq7KV4g0/FYP8aI4zOqC6vA8Dre1CY=": {
            "valueMac": {
              "type": "Buffer",
              "data": "v9zY+Ei4ZAScJVp7KpSyaFilRBzUY+BL8PZz9AhwRM8="
            }
          },
          "zH1SIvXLl8v9n8MTF8NTAh6XyfOHuncDE7I1NL2TNhA=": {
            "valueMac": {
              "type": "Buffer",
              "data": "7cSR/C5SoJDpoyC69Z1zM7vWofihd2bvufeWitdu9Wo="
            }
          },
          "GI+3ywGCdHklQUZYyaiEj+nAjIqX6/gWTBd9D9s6MJk=": {
            "valueMac": {
              "type": "Buffer",
              "data": "aYZPwJQTqgCSnmmMqUT+KFhe+PCmfS1/75e7tir9fHI="
            }
          },
          "ZPYh9NqYBc0Jq6wFYuRCYBJjs6dwz11SCLLmF1EEe/A=": {
            "valueMac": {
              "type": "Buffer",
              "data": "HbRv3d4+h+CKJ8fCEBeA1D+mWAYAqPRDX0TpoUofl+0="
            }
          },
          "7LT9Vis55Q2zfK8UjuZre0osAzJ/9RtFLy7knU0HCcc=": {
            "valueMac": {
              "type": "Buffer",
              "data": "aieQC7s8GJPvFDQr7gBPCJ8D4M0v7il1b5KiwfDCB5I="
            }
          },
          "3/miQdAvPZHEin/2knLn2s7e1wcf4k9F1oE61Fuk1xY=": {
            "valueMac": {
              "type": "Buffer",
              "data": "TrYUVRG6lWCCQOnNU+mTwN/gRmIqxfSX0OHCjRXypn8="
            }
          },
          "fRYsBs34NsFR3DC1hPo5i2Flk9Ygqz1Ka2ONSOSM0+o=": {
            "valueMac": {
              "type": "Buffer",
              "data": "pCwRSC+vpmIWou5DYck29yCjvas7zhh3lSSmQgHEHzg="
            }
          },
          "TYEI5V3pzgaO0h9uTnMOLZdrIALyg0oL6D8GQpBGwNI=": {
            "valueMac": {
              "type": "Buffer",
              "data": "sSd3/u9p4L7HXlA70dVZDMzWlKNcNLlL2OKSd+PnjXc="
            }
          },
          "PGz6IUIBFT0Ie5WR/D6ilEEZZawLfKi4YZLCL/cgYOw=": {
            "valueMac": {
              "type": "Buffer",
              "data": "lG2W2HSx6RnYVZRI95GiuEBZ/v80741chkfAlAzGvz8="
            }
          },
          "hoFIOtQdPPZbrUB+1p7kfAsnfqHHXMZAoJWN/8KtPMI=": {
            "valueMac": {
              "type": "Buffer",
              "data": "HM8Fa8oSUsPJozsvDG3leI634Z15bmkiP0sGnOKsEKY="
            }
          },
          "MpCNINlvNeKyxgqSQec6YMmXDdVwFVHXbwF7w98SBpE=": {
            "valueMac": {
              "type": "Buffer",
              "data": "xSfTiZUrEodk6pWJL45/PO5L3DxsSyYlUs/6nRYtVNU="
            }
          },
          "mi6Xs1kMhLlHsh5V0ZdV5V4OYK8v5jwqNgm5TDR1UL8=": {
            "valueMac": {
              "type": "Buffer",
              "data": "u6p4w2vTdNqXggpw2Gefdb05oqKVuhvaJ3cfEbF71jM="
            }
          },
          "mvFchVhnYi/ajzZbZehR4KFMBTVvFb0ZsFCqp1rW5/4=": {
            "valueMac": {
              "type": "Buffer",
              "data": "6ej7Kj1i3CKtiJLAgxuPZT2e91iI0CrXHzmQtgaVelc="
            }
          },
          "Lb8BuY7DJHWq0xA+W60kkaG28huAkaiq7p3m6+mQvUA=": {
            "valueMac": {
              "type": "Buffer",
              "data": "Ha46d5bcp3++0DhDOW2Yb2K6v/weZ0dkfybEBoLpE0I="
            }
          },
          "8kZGnIRp3iic3/G944sru2NXFJcXbi4TVr2Wb55oxMg=": {
            "valueMac": {
              "type": "Buffer",
              "data": "uH5T7DaYasA8elrQVDmaAHgroWC1yCLWxFNBhCeeXxw="
            }
          },
          "3EyqVZ25D5tgX7V2HMBG0OU69xz91fTq83/aR71l7es=": {
            "valueMac": {
              "type": "Buffer",
              "data": "xffCDKh8aSE/cGIbYY8b3pw74AfTghL8GrUlphoyikk="
            }
          },
          "w0TSkEaqxY+4vbvVrs7Bm9tzKGcHIY31Xi/TYHbELA8=": {
            "valueMac": {
              "type": "Buffer",
              "data": "/ZSncMpRSTy8oYrBK+GF2ftYa+wsgybJAAPMLOx9B2o="
            }
          },
          "SgaKDCbUeyRI5xpUpOWF7zn5ydMM4meduFWNaXW7SYM=": {
            "valueMac": {
              "type": "Buffer",
              "data": "jBQUr31a5UNzFyvgTQA/ztDpg+B1Qhp1nIQw6mbmBOs="
            }
          },
          "cDw18rdAbTt8wVu3JS8/WCcoMILFvNTBWeNOoP7YJ/k=": {
            "valueMac": {
              "type": "Buffer",
              "data": "9qz+uT3xl+3IWEs2d4qOzvWrK6mxVWV0M4GlO34cgV4="
            }
          },
          "HdTEYzi89T3YBW8X5kZKzr2OHaj4i0QUJ99xE/5yJdA=": {
            "valueMac": {
              "type": "Buffer",
              "data": "Cqzbnpi6MUx8gnCXXHF4rauT1fUrQ/kkL0y9/ZHrUlA="
            }
          },
          "yTaAlIH0NnsHuG1DxLdMW0Hs/DIb8TKEunYiTx/EG4s=": {
            "valueMac": {
              "type": "Buffer",
              "data": "gL3fKsWzYCHphj3wDnrdUrZLf7xM7zyKJyBh3KEmQ9c="
            }
          },
          "Hf2C4KIuUPLmMqUjxWw5ccD454NK49wmp+i4R/aSLeE=": {
            "valueMac": {
              "type": "Buffer",
              "data": "AAJ4fKiAf3EIa7H0oPljUIJCuYngyFYEBkWLC+ofhms="
            }
          },
          "eh78rwDfctuf4qitoH5flK2avk52TQBDxelroZcgPCw=": {
            "valueMac": {
              "type": "Buffer",
              "data": "qMgYWcVZ44stKl8L6S5FZLGFvs0GOssCXAymyAF+UMQ="
            }
          },
          "HT84IrKIEviLyvIpeB5vfoRjatrtS443QKfZYtdulB0=": {
            "valueMac": {
              "type": "Buffer",
              "data": "tT+rcgcYxJ8LOz04X62AcwhH+utQPK051lx3lrxbBv4="
            }
          },
          "ePVoi7NcAz+Bu4zrnlB4rUH/0Nbvkvwx4ABZQx8RCjU=": {
            "valueMac": {
              "type": "Buffer",
              "data": "w3r8KP2k1HptZ72bol3z8IrkZTNZFlvko/+R0VrLkOU="
            }
          },
          "J14/EgiSPT7GOB7jQGd/rTj74l9I8u0lVEVg9HxnH9M=": {
            "valueMac": {
              "type": "Buffer",
              "data": "160rNY7LX8kVycr8sTxM80v2lzue790IeuOAwIjiG1Q="
            }
          },
          "Hi/OS6IvRs06BcOoredg1a5g/+D9M5SPHpyVU9I1cvs=": {
            "valueMac": {
              "type": "Buffer",
              "data": "cH/cJc7KDAvU7FZx1CJIvcXEUZEzQr8HBNuKcVy1Z44="
            }
          },
          "gP/u3EC4UWqRimqgj8gUFmtTR5j/gM9enmRnJOpXM4g=": {
            "valueMac": {
              "type": "Buffer",
              "data": "/MV83MQ4EbjmfUtDKICdoDddvttWczG1b01jKV/JQCs="
            }
          },
          "FUWUUgsK5332vEghex0mqNACGfrzWdpSWWnI8AmRcAc=": {
            "valueMac": {
              "type": "Buffer",
              "data": "Sn+1BNUhOWzLpLWgYd+hkX6ry/4sKMPkOWGtccS8eKg="
            }
          },
          "wNiuT/jTkxAYC7NGjVQto6x3O6q5cjjEecP/X3NKcUc=": {
            "valueMac": {
              "type": "Buffer",
              "data": "/PAQkm2BU4+K+jT0a8MDIatuZ+/AfK7A0bAMH7Z3UjI="
            }
          },
          "5Mqw5KOge1BP+ziHtVXCuM/qQvKL6wW78LyefQtHnSk=": {
            "valueMac": {
              "type": "Buffer",
              "data": "4PBzZDL1X+FiK1Ozw3K8h3iFJkz0RLK7p6Fz34DZ0Gs="
            }
          },
          "+yoNJPRYnlBH5scyetdBMHdkRwn+evdnFmQK56VL6Q8=": {
            "valueMac": {
              "type": "Buffer",
              "data": "3mgPEhjGVWXr+/Iwji72Tcu5NsUcwN47L8V/KHigdJ4="
            }
          },
          "q5N8Ie0ShYwVGamuj9BVUvb6+jJiTSpTttf/S+veD/Q=": {
            "valueMac": {
              "type": "Buffer",
              "data": "04pgKXjDhAMTJwWkqnsBlKAb2SJVTUDqLHNslNKOxso="
            }
          },
          "lzlu/BVjalFa8SQTMiWqole/s45bakcZUggzfAtOOHs=": {
            "valueMac": {
              "type": "Buffer",
              "data": "qfPbmeolOY+byWko29e3DTbMiktrbZFdgqozagsb848="
            }
          },
          "HOgtlOAZureqgWP3ch0oP2W91bLP//ooVTRvo9t+erk=": {
            "valueMac": {
              "type": "Buffer",
              "data": "4KcNAxwwkXQb0qRaHsAkcrlgC0hqtouiy9MfMi3Uij0="
            }
          },
          "eboEkYqz7q1VQp6sZ35deC0RXAfKQR7xR/8kIegAf9c=": {
            "valueMac": {
              "type": "Buffer",
              "data": "jDt7A1jMwbYnKxIQpTz4td6eUwcyyKK1NflGWdkG0tg="
            }
          },
          "K4yAicCEIix4d6AJ+MBsAoVH0/G17uKRGN9PIJlCLtQ=": {
            "valueMac": {
              "type": "Buffer",
              "data": "BCJYZZoW1WaSYPzxn+N8FBXC4sUb0cPP2mDccyY39mw="
            }
          },
          "hQRkqgq0J2EbJ2sGmW11Oy30JvlTcwQtu4UXnlMJS1o=": {
            "valueMac": {
              "type": "Buffer",
              "data": "rRpIcDZCM5iX7SDqQbpD/9msig3FkAGN2m/9+ytayxs="
            }
          },
          "snKbzvCLmpQ1yeX1vs2PSFlkdwWLJtpqE0mqzUj93Ww=": {
            "valueMac": {
              "type": "Buffer",
              "data": "YDQ7JqT88BpIBjv4hVc2TBevdUl6Ysb70aRtOyWq3eA="
            }
          },
          "AQOdZIFNg5G79MNViP1vCObwV9aaFFbFBljdcqsxgNM=": {
            "valueMac": {
              "type": "Buffer",
              "data": "Jq57B2yQsiCX1L2QbZGJUEDEB12BNUjtDnMs8QrIGqs="
            }
          },
          "VicuqYMduc/PImm19mkmnOdjfaqmASXCJcaGN1w7PZ0=": {
            "valueMac": {
              "type": "Buffer",
              "data": "cipREGV7QJZgpjBdeDAQOFodj4KB08kN9t154G0Nc3U="
            }
          },
          "k+JiblumKoGmn20naub+oj/0yVElUx83jbQ+7tvLKzQ=": {
            "valueMac": {
              "type": "Buffer",
              "data": "j8M1Exjoc467wZtH3OVVlyU2CLCcqRSywgfbEOcArDo="
            }
          },
          "wSYx06n9PFAY54fyQORbNJhfVGbV1eNOtINq/g/Z/6I=": {
            "valueMac": {
              "type": "Buffer",
              "data": "hZaI0yKKgosblMcV9Smz/f1as5kqMdG1m89deFp8REw="
            }
          },
          "6RA43S44t/7IbUiux9plPcqINFaI65DYb5Lq0395upc=": {
            "valueMac": {
              "type": "Buffer",
              "data": "pr5S0RKfEOyiWNJfqpNAIYJodNoL5dwQbde88aSqUAc="
            }
          },
          "qNrbxttSY9rbFeZ2Mt4iM36IO27aZ6ABx2YxVLJIObo=": {
            "valueMac": {
              "type": "Buffer",
              "data": "P13zxuN6LbOl/QuLMlPtuS81BuKqHxJdmH0FggnVdrI="
            }
          },
          "BbgH5TliNxU2NdbsrL1s37ZX/qumSmGvryqBfoFJlbw=": {
            "valueMac": {
              "type": "Buffer",
              "data": "tDAs9TFb2/5Ep5WFoJhxebgHIac9Hcoq+OpJyB8AIC8="
            }
          },
          "v3SL6qn5t1rdLbpjJXSJ3Ab8O3Zxqo2LM5c33KAOMRA=": {
            "valueMac": {
              "type": "Buffer",
              "data": "D2F7FO3TQktyatRKCNjLwe6JxuwH/1Btwok5ZMoUjqk="
            }
          },
          "HHPj5zT7xkeBKXHu+XOf6eT2ZJdlJjPnCHhenq+25pY=": {
            "valueMac": {
              "type": "Buffer",
              "data": "PodIzak1G1jFR86b1395bs/bGpMf/bPWPalPCYFVNXM="
            }
          },
          "ET5v7O3U1VdPo2UaONwbjr8LzAMjZH0wgCnik8HuoY8=": {
            "valueMac": {
              "type": "Buffer",
              "data": "L4DryGl/w9XsYlf8dcaO10Cn4lTAk1b3pjCgQVl1r3A="
            }
          },
          "pteAL8WLg5yG5zYwH8ONJMeFgPSl9Z2Yk5onSWjjDTc=": {
            "valueMac": {
              "type": "Buffer",
              "data": "oO4e9l7syZwODOzE3gncKAs83i3Ma+ify/kex9ivUl4="
            }
          },
          "1e8wF3et8Y0LUjnB2d4ytuPY4eOeCYrYdo2PK1ntXvY=": {
            "valueMac": {
              "type": "Buffer",
              "data": "EmvtnIe4oTrVD+wqU34frnzA+I12rMAygkqA7On1y9w="
            }
          },
          "PGhknieXdF7t608KMhTZSgcpZzLb06JUJqsc2zrwdNs=": {
            "valueMac": {
              "type": "Buffer",
              "data": "r/lrZV9lWiLWsUtQbh14wHxkL4pfrmxeygyeIiMqrbw="
            }
          },
          "PyLViQDXnnW6CILakMYh54xgRtmMaCROQwnoOiWMYKY=": {
            "valueMac": {
              "type": "Buffer",
              "data": "LhvDOKeD7YS00RovNDHj8QrjYcXzzsFCi1wcaTo1Kc8="
            }
          },
          "PFnIEPobTSu2GRn/sGLDfmWXRZYNp4PSbCyjkg+5gtk=": {
            "valueMac": {
              "type": "Buffer",
              "data": "WFi0HP8OsZ5wIc69VFY3YJ5jvetDfa8B4QDHmST2UiE="
            }
          },
          "ixqqvmw6a4UTrr8I6Jmu/UKUb/dAPz+LulymT91J5Uk=": {
            "valueMac": {
              "type": "Buffer",
              "data": "GkwujhlGXpG7lYHee+G54OKqC1cimxZM1NDI+s8yuTg="
            }
          },
          "/HnX1DnGq4I1RZg7cQJeCd3ZMOGDg6TK4AMQmU0b+fc=": {
            "valueMac": {
              "type": "Buffer",
              "data": "f3USI9+vFM6LhIKNDVhm79FGNspza3Ozz2z5kRyN4wQ="
            }
          },
          "x3U5yGgdpTtro0PM11TKM3T2tB4kZzp3yQcTWIq1y3w=": {
            "valueMac": {
              "type": "Buffer",
              "data": "p2OLiULY4+Min3cMdYM19BgMTYpUtzd72e+yB/b0wug="
            }
          },
          "J43iJj28P8tPYZgUJZb0I372jpFme9HnzSH5vPUBabM=": {
            "valueMac": {
              "type": "Buffer",
              "data": "KYe/CoRaRAtmbkMHt//JrzuRwP7TCjNUW6juIHxxQdM="
            }
          },
          "xlux01hnSC4yte26ULnHEpyeOvtA1sisQc4tVPlQXYg=": {
            "valueMac": {
              "type": "Buffer",
              "data": "RYJeCJDuC8VrTzRLDx4vph5aE8XjdHkVgH5IEYNs7SA="
            }
          },
          "sM/ARfIrRryYW8P1NGXM1ib/Ryj+zDkbMS8gtVcSHNw=": {
            "valueMac": {
              "type": "Buffer",
              "data": "lZVlk4BwUdo2vFOByLXwLgD8c7ddazuUxmeajL/Ncz8="
            }
          },
          "37eAdfZTOz4zCHITRqZVWwZnpPUmPCym2jTyccdcq40=": {
            "valueMac": {
              "type": "Buffer",
              "data": "b6jt8XAXW2TqZwwbZ4E4ey4KY/ZS07bjEvM8ae98rno="
            }
          },
          "z8o79MofwS3SNsXtZZA0UeePn9aO1gJ6Me4KM/TVuRM=": {
            "valueMac": {
              "type": "Buffer",
              "data": "3TZkVV8GSYx7tR8MFHZxdthUBmblqZxH0L7C2yJhA9Y="
            }
          },
          "dwQQqmDyUOscfdpUQMBLNVlEbHuIdqQEdYxvX+M0RNU=": {
            "valueMac": {
              "type": "Buffer",
              "data": "EmP0Znv0VgaNB6WyOfj+8EW8pgEJ/qKrMVUXIaYgxM4="
            }
          },
          "yaNQPYliXQ0jZBiLQGPccaQUFYEm4knMXDMoqIbOLEM=": {
            "valueMac": {
              "type": "Buffer",
              "data": "WZjeg7/i4U1OD3aa9Ne+n970h/4sNSABxX8cSxV7kos="
            }
          },
          "TwA/dN7PRJFJqHSxmqNvRC1EJBzorqcoSn24TrAUwBI=": {
            "valueMac": {
              "type": "Buffer",
              "data": "rW5PSQgMyBd6O1bz5QF1efqnuwm5KlBBW0kI+7dqekU="
            }
          },
          "Yt8ZtWX8Mx8zubjFbSuaSxe0u2xoYpqbpEpMKodZHNk=": {
            "valueMac": {
              "type": "Buffer",
              "data": "AJFza0hkdawXabWHx7noXa1EOwZhRhjetc3gpYIwjoM="
            }
          },
          "XfNG8S5X++plYrU6MFqttDMvFuTNPZWCYFfMHoZYeWQ=": {
            "valueMac": {
              "type": "Buffer",
              "data": "QMMy1DOpR/VuTMeFFPVj8pcHPbexLW3cLB6eF45t3s0="
            }
          },
          "rybXRRi8QIQdeNjZWbod4EJUzWuiwA5oL+FOGkYUHoc=": {
            "valueMac": {
              "type": "Buffer",
              "data": "gPYmxjShZBsddJh1/apXDf4h3Bp7k1+6Rr3GkN/gf70="
            }
          },
          "oVrZrBIrXqp1eSEJwbbHU2ghTYTFXZT+BXpzfhLTjCI=": {
            "valueMac": {
              "type": "Buffer",
              "data": "pqz7+ysJcMDp8U9HONsWfClS3ip/Pq8CCROg6dbgiU0="
            }
          },
          "lKOoAVH6/1HwqOo3wlS5msG+z//dK7GoWH3ctJTQoRc=": {
            "valueMac": {
              "type": "Buffer",
              "data": "8jospkh7wt6IZKg5fV61F9R94X4R6d3TE5YrV+/0XuI="
            }
          },
          "jPTDHVdERoaA8rLlnMXbvMTTJ53rphUQxjRgANrlM0k=": {
            "valueMac": {
              "type": "Buffer",
              "data": "gTrs4+S2j/dV5VDplXP0xcuR4AWR0aqd6za3K5x91FY="
            }
          },
          "Xi59rviCrzEM8j6Nq1tAiS/y4dyx8ovRwYzGcG14Oqw=": {
            "valueMac": {
              "type": "Buffer",
              "data": "3IvyWH8cNbreMRavoB7d1ZIOz3jkdYRM53d9Fy/4+Oo="
            }
          },
          "hVHD58iOk9NNsRucuHXFW8eCK4+sySQCtRlL5FONUDw=": {
            "valueMac": {
              "type": "Buffer",
              "data": "UGYyxrkTP7oVScT6Wi0WINMclebl/2GFK8u/DY9SLRw="
            }
          },
          "J198yrY2yrMq3m7ejF38UX91qN7u88ey67d1J3yuX14=": {
            "valueMac": {
              "type": "Buffer",
              "data": "hhH4mBIYuJQyZOLExg6uyMu3eRDxmjLQydUR7DXRH0Y="
            }
          },
          "HIbHGthTzlzcjxf1t84JI7ogoWk4N6OMJh7H/t3liC0=": {
            "valueMac": {
              "type": "Buffer",
              "data": "ngOuzgSzwQyL6gBpCWzfrWyJCUlEWSTm5E9Ike+mh5o="
            }
          },
          "0UdqptBv5/PPJ4ZvuNVu+J2kQvQizVKYzAORQY3DPs0=": {
            "valueMac": {
              "type": "Buffer",
              "data": "lHPxXPRaU01YsKSs0o+nPV1eXK1nsv7jCWYVnSpoZXE="
            }
          },
          "WlePtVrXSXvyfSJCdfdE4SI26aaibk3GL4xsWH8Euqs=": {
            "valueMac": {
              "type": "Buffer",
              "data": "xL/imW5/qV87qrNlmOw61agH5bYn1pSU+gkH7jbFM0U="
            }
          },
          "M9Imfwq7Xqzi/DjhVYZ+mn1b/YmOkBFjG3GzTClwINs=": {
            "valueMac": {
              "type": "Buffer",
              "data": "4xR3o6X90LJpG5zBsxi21nZG93ZIl6n4HjFYJ34TJnY="
            }
          },
          "u78DjULNlrcl0jEpeeMJe+LT0FgwoEX49nIQ16dmeik=": {
            "valueMac": {
              "type": "Buffer",
              "data": "aCs++gnVgv5P2avX3oBeyuJcThT4hWflke88KGCQ0xU="
            }
          },
          "98CIxpz/xlqPHfvLHkd9chjy7mEjO9xtRD5kd1eOw3Y=": {
            "valueMac": {
              "type": "Buffer",
              "data": "6FgAnD2z9vz3FGYVHzRvziX87QhDiMiQXH4kPollD6c="
            }
          },
          "F6cz3e/RVRI1WK5r9x+l21t/7K89VnDy9mzvnSgIEcw=": {
            "valueMac": {
              "type": "Buffer",
              "data": "/Gfc2l+tg3Je48p4eq0zwW+ZYV7L5sakPN5s+gIrxyo="
            }
          },
          "NQPTQeJYSY+fAXw6v0MjCekIwiGfywSKGcCmu0g43qM=": {
            "valueMac": {
              "type": "Buffer",
              "data": "47Kk8y/AbtRjSphA1XjdAPyYhrjitdbaV4oB4UaPhRs="
            }
          },
          "qhvJno4tPGthA20z6BDoMZ3wUQqzNzSn3Uc2tsVsrBY=": {
            "valueMac": {
              "type": "Buffer",
              "data": "nuf/eCcatjBUdSIafn/T6ADLYBpCvWQ2gSfMLFl7o5g="
            }
          },
          "C+Mxveh/JxMPtkzKdfNGybAd5pNt6NlaW77/yShFIf8=": {
            "valueMac": {
              "type": "Buffer",
              "data": "2d4X0kDEDJgxYar7xOKvW/dwzO/dg6amjXI8z831S8Q="
            }
          },
          "XqSlgQwAjSyD0ojQ91U3lQTBdzEwa6tMzPquHC4/A68=": {
            "valueMac": {
              "type": "Buffer",
              "data": "2kh5w3aqx9EvW1NCBrFQfzD8FCYwEGcIbFIiZn5WB18="
            }
          },
          "Op79LBzfKnll1zIJHZEwyiXfX7JH8qLzUJnnpMhyWaI=": {
            "valueMac": {
              "type": "Buffer",
              "data": "klAwo+0SPWRzhQ7akI/XaZNFpHshU9Gt/be9YRj0MYw="
            }
          },
          "oX2MrR3/GMQh//haYKYiHQR1EyHjBn3Ph8q+3aQxLCo=": {
            "valueMac": {
              "type": "Buffer",
              "data": "nWxfmELSce6j7EbU08yj37n2eBC3391cgA6SsyZRZYY="
            }
          },
          "a8Jj8c1jwKyTKp4Tu4Ni+jiTmvsy2IZOnPzXEKnQmkQ=": {
            "valueMac": {
              "type": "Buffer",
              "data": "pi+J5vmLnPkSMa3+S1Cs+GpdkthHNjBjuTOQKgifmx0="
            }
          },
          "32GNk3W7o/QT4yNReTeO5EtUlAGYYnPhI1z8he+q+lY=": {
            "valueMac": {
              "type": "Buffer",
              "data": "b40giIaLXrhKSxQTBWKkRERuG4eQ1Yd4pfBPVSfEAOA="
            }
          },
          "egtvXC1OkaGs86/vhO0a2b8gpPCAkTpTFrEh4KGhhoA=": {
            "valueMac": {
              "type": "Buffer",
              "data": "HSvI+lvPi1jQzkPqK8v1DWG53KJGQF4KatpLZiaPnrM="
            }
          },
          "Nhmb547zBGgmOqoHQViY9IXYdkdM7JXABWXfzwN/7tE=": {
            "valueMac": {
              "type": "Buffer",
              "data": "N/HXQPS19FXpWmw+R55pppwLnKGgaoaBCTjmYnB3TT8="
            }
          },
          "M05VG5yfjdt2Xj9uWSNJ3v4VvxUW6w+7GvXWEbjNsCU=": {
            "valueMac": {
              "type": "Buffer",
              "data": "Efy4THgcTsa9lNOhFgwGC9J2DxAH0MOluIKNPOomPNY="
            }
          },
          "ij6jzBWa6SaW14zeJePnG4Jusp3OYITvv11TisGWmIw=": {
            "valueMac": {
              "type": "Buffer",
              "data": "kifd79i69AJBc5E36GLx9USXzLNhD++oC0fJCSvwf54="
            }
          },
          "j028jz4vMGiHt4lB2YwWeIx4618DIPzB+ZQ9xa0PT24=": {
            "valueMac": {
              "type": "Buffer",
              "data": "tryk8GZtrVO+xTVT9QMpFS+yIpq2u1mzAhT/JS9BiQo="
            }
          },
          "afTvpgZ4IiqsUP0sYXLEsrvTSAdHHef7LC3TvsRgYlA=": {
            "valueMac": {
              "type": "Buffer",
              "data": "LbzcMvmw23eR2nOVcxUQTI30Q7rmq2iRgAykdORGChM="
            }
          },
          "RFSjXwDBWFH75KZiUCMbTohEXP70Z77KjhI2i3gNmf4=": {
            "valueMac": {
              "type": "Buffer",
              "data": "wq3X2IU9+zNV8fFTLCpBWX1eKQx24p/E03IpxNHd2hw="
            }
          },
          "ZxrDnEgua6yd8dVvF9WSBsGEd4GtCcRMye68LC+GvdQ=": {
            "valueMac": {
              "type": "Buffer",
              "data": "LO76QkI5cEScBsMmawwEIXuDrEAmBwxLUqUTbZWJ5nY="
            }
          },
          "zvCwMYrQyiPB8hxtD94rxYfzspC96sagNdUnh1dbkLA=": {
            "valueMac": {
              "type": "Buffer",
              "data": "6kmbVI2CqRPz1N9h8Lp43JNElZxASEb5rJ7Fcv2TOzk="
            }
          },
          "04e+AzO9TmpP67L0sDJxHkXjEw59l6UtoymOsne4uZI=": {
            "valueMac": {
              "type": "Buffer",
              "data": "ZPKJRCNGZ7OAxgoyfNh81xBYZBjYQ9tD/HCpPK3Xsl4="
            }
          },
          "RQpuCd+4VOBdX+ZHpnNxZteo+VfWZDeep8rk3PZfT1E=": {
            "valueMac": {
              "type": "Buffer",
              "data": "fnnXCHu+jBVRaFrdRYyvAJ1/k8s0bZAwMaUqclr82cE="
            }
          },
          "FgExNsljhLBvuquHZk+9oBqjdwyyPLOqef+pRvSlbMI=": {
            "valueMac": {
              "type": "Buffer",
              "data": "Lg9ITm/nCQgUiv9A5MZw/MSQtlNy5krF3DOuCfafltc="
            }
          },
          "obdrdO+wu7tGmeaAbIi+jdvYAW4KcjeEdizh7OM+Vd4=": {
            "valueMac": {
              "type": "Buffer",
              "data": "zJzjf7j2bz6b0N5ZRUz8bg7Dop2H9lFojcapyP69944="
            }
          },
          "VhAOvtxeslIls52rn6wXdDrDxHdhH0fg1a79Afbclpw=": {
            "valueMac": {
              "type": "Buffer",
              "data": "iIsDQkt26CvKq6o7cwwtifMvBr4TRL6f46ijFYQu0yA="
            }
          },
          "grmb1jO3UTkCzqlKQBPsHBBTTWx2rnb101D6nfxDYRo=": {
            "valueMac": {
              "type": "Buffer",
              "data": "p2xZnIFb2Iw5Hb3R7G96YKdyRcWM/sImTlJQv9zeK+4="
            }
          },
          "prmpkOqZB6XUsDxS/pNHK4mHLnK01QGwpedMfTLrcEI=": {
            "valueMac": {
              "type": "Buffer",
              "data": "jNRQxE9QNFVOAqTYV1TYZH0RB7IrJXwAGfcGmwmvfxM="
            }
          },
          "zkA/zjotJOwu5WEJMuN9WV3Apz7+XhD1hVDD6ajZovU=": {
            "valueMac": {
              "type": "Buffer",
              "data": "HmuHqifOGfzekLAscerPT5EvT/6FrdaX8sF3UL7pPgA="
            }
          },
          "FO7jaeCN2czhEMYr/JtQ244DEkFhfr3nYglZZxktWr4=": {
            "valueMac": {
              "type": "Buffer",
              "data": "psPqQJVB/x6B97I0XzZkzkaOoAFNpOoiCjeYmzn7ZQA="
            }
          },
          "ClX8ARs5ZSum/CYsETqBb0q5tmf2MVMIWfvL//kc3WQ=": {
            "valueMac": {
              "type": "Buffer",
              "data": "XBSyLeFJW9Jh5A2qvfcXKzjGrzJCdPrhbQFOAfRDFps="
            }
          },
          "GO66221su3sEUiPmigaC6mMrkPtlH/epif69vKzd5M4=": {
            "valueMac": {
              "type": "Buffer",
              "data": "LFaAJDG76hrlLBopZ5uXEekhijeGG1AdMigDLqE5iNc="
            }
          },
          "HNWz/tQTB5xQ+/PpXZOJ++ZOrhRk4lZ4hBEWe6HkO9Y=": {
            "valueMac": {
              "type": "Buffer",
              "data": "/UieFvvJwQMPpaqpir1o3Wdk5YSFUhZuYAEf1A8Ywus="
            }
          },
          "DstKQv6E0GVHeeyksh82j9vJPRsZWgdZSHfqtHMi3cU=": {
            "valueMac": {
              "type": "Buffer",
              "data": "Hwq5WEiVVsikhOvTszXe6Lz24zJSCZON+zpBUG4U1Mk="
            }
          },
          "0Sv+gPN/X9K7Uk75VO6cm4feOVU8JaCe7kFf511AxCw=": {
            "valueMac": {
              "type": "Buffer",
              "data": "hAZC4m/8Mhn14DEcvruplzCY5kD/LigPfXfedsD0yNQ="
            }
          },
          "yDr9B3BL01koGwvSF2+HuMmVxTupVg3MZTrZS6guQ1g=": {
            "valueMac": {
              "type": "Buffer",
              "data": "jVNWagdlXc8oki3YpWdAWu+AyRL0/vwrLU1uozBYiyE="
            }
          },
          "YmPZwr9Fgq24tWOG1HRqvvpSg9XWGjX+WUmIsPIVKaM=": {
            "valueMac": {
              "type": "Buffer",
              "data": "GhEK+L7ky2DcpwXUn4Te3uBPcptl0021jsez9lWLZfo="
            }
          },
          "WXLWjv+KKBmnWigD0j3x0yVyi624WMID/qSEg++uU9M=": {
            "valueMac": {
              "type": "Buffer",
              "data": "n3oybQkEq1xnZ1igfwjzbeIKyYVTgv3eHUJ8ZPRQg6Y="
            }
          },
          "bIbQnopArYNnM5r6h+Xq4SkMY+iVZHV/ysMCD984Ads=": {
            "valueMac": {
              "type": "Buffer",
              "data": "2mFI5Pc5kSVgRfFH9F76ukRSqQcnyN53DefaOaZHvrs="
            }
          },
          "zCFjOWghdTY5f+I6qsU8JLZxu/ht8H156hkap4eYGCI=": {
            "valueMac": {
              "type": "Buffer",
              "data": "eFhlNxJhMjFNqI5Qu8BTZZre/+JmjqT2gjQYbABZ+kU="
            }
          },
          "rRKgXfQBQDxrR/nG6wIxpOnOSURc/vU2mPVcGuyxGtA=": {
            "valueMac": {
              "type": "Buffer",
              "data": "i3ci0ms8abr6nS+yKr9+zV+IAIffptC+L7geaNIw7uA="
            }
          },
          "pF9WnbNePhxlnmWFvOc/AXK1CWXEHKOjRzAIuGyaZLc=": {
            "valueMac": {
              "type": "Buffer",
              "data": "pNtrUWhdmjkniNxGdVM9DQ+4Hv8D3m6lj5CosNJL3bk="
            }
          },
          "sq/LIBxN7iqpmckheRtMPpDJjuQB6YtBDXhMbqjv7As=": {
            "valueMac": {
              "type": "Buffer",
              "data": "Bzuol60RRDemhuYKShT52hHceztbY7uWlY3Lq5D/M7c="
            }
          },
          "vsVTguPwbu+NzIP84+Gj1TnwB+UxHfxBR6B6pFGlcKQ=": {
            "valueMac": {
              "type": "Buffer",
              "data": "QEjmLGdZfe5j71DnwaA6Oc3LtACQIRCBfKlQwSLAwGs="
            }
          },
          "aCoVBKzvEKwhfQF5mCVe7rWVSIuCNFHyzU0EXwAmnyU=": {
            "valueMac": {
              "type": "Buffer",
              "data": "A+DhKqflnFe1TMLMDeZoZfCG6ML7PJadcwEqXnO/CVg="
            }
          },
          "Y1AULY5xhPDhYaReY/kq1crnMIjAI6HijxWKJF8x7mM=": {
            "valueMac": {
              "type": "Buffer",
              "data": "xTt84PSl85nNTabit7iCzggsi4XaW/EHouPvmA0bBPM="
            }
          }
        }
      },
      "regular_low": {
        "version": 1,
        "hash": {
          "type": "Buffer",
          "data": "C2lFk9MfpigzCqFJ+PL515W2WTxvxnpZHdD+EdUC4LPLIaHzfuuoPbVBguVfDFa3rPpsPzN3vdXW5ZdEG2FBIFniZ/4SBIIFSSvmpyoG5KTZj2EARR6iIJ5Xp1zvOiE9utsTKoDGziRTQ7ie20ZiQtQ3iOKvOl7iZlf9Viwv5c8="
        },
        "indexValueMap": {
          "2r0cq2Cxwna/d9MsBcP3AXn7WL8o8sXbnMnjB8LHhZs=": {
            "valueMac": {
              "type": "Buffer",
              "data": "K0ofz3MtMxVUZwiZAc45rS1dsbc/pAHlXMoIZWmLgSQ="
            }
          },
          "j0dJ2n2AOB/Nuk0i7XmYbRcy+RlurpF5wFs9VqP5UL0=": {
            "valueMac": {
              "type": "Buffer",
              "data": "0gT9Q9c8VXjQ5p9EjEwyHceivwLRXaaFzjgkRQ90170="
            }
          },
          "QnRnjwLYwFLloxpl/h0qhubJlQhU06inF8auzega2B8=": {
            "valueMac": {
              "type": "Buffer",
              "data": "dVHd9/Y+atKyibZuaab2oKxmSiyzzt7ct6Gwu/zaHaU="
            }
          },
          "f3hJ/chmr0a+JYHi928TkThxGS5ekUPKGxEf7EsMhPI=": {
            "valueMac": {
              "type": "Buffer",
              "data": "qSbHXziRQMFbAi95TLNWw9gERKZ5i4N74uhd71RFulw="
            }
          },
          "P9U7YlPzoY/QXcZZiYR21bZWHkcAaObCUx+8Y0Dap2E=": {
            "valueMac": {
              "type": "Buffer",
              "data": "6KFA/gJsiLhRgTKoTfoUHq385201Qjf2Tj6L3ntGRrM="
            }
          }
        }
      }
    }
  }
}